MANIFEST.in
README.txt
setup.cfg
setup.py
ceptacle/__init__.py
ceptacle/application.py
ceptacle/architecture.py
ceptacle/config.py
ceptacle/debugging.py
ceptacle/encoding.py
ceptacle/network.py
ceptacle/packaging.py
ceptacle/runtime.py
ceptacle/security.py
ceptacle/server.py
ceptacle/storage.py
ceptacle.egg-info/PKG-INFO
ceptacle.egg-info/SOURCES.txt
ceptacle.egg-info/dependency_links.txt
ceptacle.egg-info/top_level.txt
ceptacle/bus/__init__.py
ceptacle/bus/services.py
ceptacle/bus/spline.py
ceptacle/bus/partners/__init__.py
ceptacle/bus/partners/adhoc.py
ceptacle/bus/partners/cluster.py
ceptacle/bus/partners/main.py
ceptacle/client/__init__.py
ceptacle/client/cli.py
ceptacle/client/support.py
ceptacle/servicelib/__init__.py
ceptacle/servicelib/cron.py
ceptacle/servicelib/docmgr.py
ceptacle/servicelib/registry.py
ceptacle/servicelib/web/__init__.py
ceptacle/servicelib/web/falcon/__init__.py
ceptacle/servicelib/web/falcon/manage.py
ceptacle/servicelib/web/falcon/settings.py
ceptacle/servicelib/web/falcon/urls.py
ceptacle/servicelib/web/falcon/views.py
ceptacle/servicelib/web/falcon/media/css/status.css
ceptacle/servicelib/web/falcon/media/images/action.png
ceptacle/servicelib/web/falcon/media/images/ceptacle_bg.png
ceptacle/servicelib/web/falcon/media/images/favicon.ico
ceptacle/servicelib/web/falcon/media/images/point.png
ceptacle/servicelib/web/falcon/media/js/status.js
ceptacle/servicelib/web/falcon/templates/page_base.html
ceptacle/servicelib/web/falcon/templates/status.html
docs/Makefile
docs/epydoc.conf.cfg
docs/source/conf.py
docs/source/_static/ceptacle_logo.png
scripts/ceptacleCmd
scripts/notemgr.py
scripts/registry-connect
scripts/registry-shutdown
scripts/registry.env
scripts/run-registry.sh
scripts/spline-shutdown
scripts/spline.cfg
scripts/spline.sh
scripts/user-login
scripts/partners/projects-repos.ptr
scripts/partners/registry.ptr
scripts/partners/skype-terminal.ptr
scripts/partners/stuphmud-autorun.ptr
scripts/partners/stuphmud.ptr
scripts/partners/web-facing.ptr
scripts/partners/westmetal.ptr